netbox_software/__init__.py
netbox_software/admin.py
netbox_software/api/__init__.py
netbox_software/api/serializers.py
netbox_software/api/urls.py
netbox_software/api/views.py
netbox_software/filtersets.py
netbox_software/forms.py
netbox_software/models.py
netbox_software/navigation.py
netbox_software/search.py
netbox_software/tables.py
netbox_software/template_content.py
netbox_software/templates/netbox_software/application.html
netbox_software/templates/netbox_software/application_edit.html
netbox_software/templates/netbox_software/applicationversion.html
netbox_software/templates/netbox_software/applicationversion_edit.html
netbox_software/templates/netbox_software/devicesoftware.html
netbox_software/templates/netbox_software/devicesoftware_edit.html
netbox_software/templates/netbox_software/devicesoftware_include.html
netbox_software/templates/netbox_software/software_edit.html
netbox_software/templates/netbox_software/softwaretype.html
netbox_software/templates/netbox_software/softwaretype_edit.html
netbox_software/templates/netbox_software/vendor.html
netbox_software/templates/netbox_software/vendor_edit.html
netbox_software/urls.py
netbox_software/views.py
netbox_software-0.2.6.dist-info/LICENSE
netbox_software-0.2.6.dist-info/METADATA
netbox_software-0.2.6.dist-info/WHEEL
netbox_software-0.2.6.dist-info/RECORD
